leNET_RTL_v1_seq/rtl/avgpool.v
// ============================================================
// avgpool.v — 2×2 Average Pooling (Sequential)
// ============================================================
// Parameterized: works for any input size and channel count.
//   Pool1: IN_H=28, IN_W=28, N_CH=6  → 14×14×6
//   Pool2: IN_H=10, IN_W=10, N_CH=16 → 5×5×16
//
// Operation per output pixel:
//   avg = (a + b + c + d + 2) >> 2
// where a,b,c,d are the four Q7.9 values in a 2×2 window,
// and +2 is the rounding bias (0.5 LSB at the >>2 output).
//
// FSM: IDLE → COMPUTE → DONE
// One output pixel per clock cycle (no multiplier needed).
// ============================================================

module avgpool #(
    parameter IN_H  = 28,
    parameter IN_W  = 28,
    parameter N_CH  = 6
)(
    input  wire        clk,
    input  wire        rst,
    input  wire        start,
    output reg         done,

    // Input read port (reads from upstream layer's output)
    output wire [12:0] in_addr,
    input  wire [15:0] in_data,

    // Output read port (downstream layer reads results)
    input  wire [12:0] out_addr,
    output wire [15:0] out_data
);

    // ────────────────────────────────────────
    // Derived parameters
    // ────────────────────────────────────────
    localparam OUT_H    = IN_H / 2;
    localparam OUT_W    = IN_W / 2;
    localparam OUT_SIZE = N_CH * OUT_H * OUT_W;

    // ────────────────────────────────────────
    // FSM states
    // ────────────────────────────────────────
    localparam S_IDLE    = 3'd0;
    localparam S_READ_A  = 3'd1;
    localparam S_READ_B  = 3'd2;
    localparam S_READ_C  = 3'd3;
    localparam S_READ_D  = 3'd4;
    localparam S_WRITE   = 3'd5;
    localparam S_DONE    = 3'd6;

    reg [2:0] state;

    // ────────────────────────────────────────
    // Output memory
    // ────────────────────────────────────────
    reg signed [15:0] out_mem [0:OUT_SIZE-1];

    assign out_data = out_mem[out_addr];

    // ────────────────────────────────────────
    // Loop counters
    // ────────────────────────────────────────
    reg [4:0] ch;      // channel
    reg [4:0] row;     // output row
    reg [4:0] col;     // output col

    // ────────────────────────────────────────
    // Datapath
    // ────────────────────────────────────────
    reg signed [17:0] acc;  // sum of 4 Q7.9 values, needs 18 bits

    // Input address generation
    // We read 4 pixels from the 2×2 window in sequence:
    //   A = (2*row,   2*col)
    //   B = (2*row,   2*col+1)
    //   C = (2*row+1, 2*col)
    //   D = (2*row+1, 2*col+1)
    // Base address in channel-major layout: ch * IN_H * IN_W + r * IN_W + c
    reg [12:0] rd_addr;
    assign in_addr = rd_addr;

    wire [4:0] base_r = row * 2;
    wire [4:0] base_c = col * 2;

    // Output address: ch * OUT_H * OUT_W + row * OUT_W + col
    wire [12:0] wr_addr = ch * (OUT_H * OUT_W) + row * OUT_W + col;

    // Average with rounding: (sum + 2) >> 2
    wire signed [15:0] avg_result = (acc + 18'sd2) >>> 2;

    // ────────────────────────────────────────
    // FSM
    // ────────────────────────────────────────
    always @(posedge clk) begin
        if (rst) begin
            state   <= S_IDLE;
            done    <= 1'b0;
            ch      <= 0;
            row     <= 0;
            col     <= 0;
            acc     <= 0;
            rd_addr <= 0;
        end
        else begin
            case (state)

                S_IDLE: begin
                    done <= 1'b0;
                    if (start) begin
                        ch  <= 0;
                        row <= 0;
                        col <= 0;
                        acc <= 0;
                        // Set up address for pixel A
                        rd_addr <= 0;  // ch=0, row=0, col=0 → addr 0
                        state   <= S_READ_A;
                    end
                end

                // Read pixel A: top-left of 2×2 window
                S_READ_A: begin
                    rd_addr <= ch * (IN_H * IN_W) + base_r * IN_W + base_c;
                    state   <= S_READ_B;
                end

                // Capture A, set up address for B: top-right
                S_READ_B: begin
                    acc     <= {{2{in_data[15]}}, in_data};  // sign-extend to 18 bits
                    rd_addr <= ch * (IN_H * IN_W) + base_r * IN_W + base_c + 1;
                    state   <= S_READ_C;
                end

                // Capture B, set up address for C: bottom-left
                S_READ_C: begin
                    acc     <= acc + {{2{in_data[15]}}, in_data};
                    rd_addr <= ch * (IN_H * IN_W) + (base_r + 1) * IN_W + base_c;
                    state   <= S_READ_D;
                end

                // Capture C, set up address for D: bottom-right
                S_READ_D: begin
                    acc     <= acc + {{2{in_data[15]}}, in_data};
                    rd_addr <= ch * (IN_H * IN_W) + (base_r + 1) * IN_W + base_c + 1;
                    state   <= S_WRITE;
                end

                // Capture D, compute average, store
                S_WRITE: begin
                    acc <= acc + {{2{in_data[15]}}, in_data};
                    // avg_result uses the updated acc — but acc updates next cycle
                    // so we compute inline here:
                    out_mem[wr_addr] <= ((acc + {{2{in_data[15]}}, in_data}) + 18'sd2) >>> 2;

                    // Advance counters
                    if (col == OUT_W - 1) begin
                        col <= 0;
                        if (row == OUT_H - 1) begin
                            row <= 0;
                            if (ch == N_CH - 1) begin
                                state <= S_DONE;
                            end
                            else begin
                                ch    <= ch + 1;
                                acc   <= 0;
                                state <= S_READ_A;
                            end
                        end
                        else begin
                            row   <= row + 1;
                            acc   <= 0;
                            state <= S_READ_A;
                        end
                    end
                    else begin
                        col   <= col + 1;
                        acc   <= 0;
                        state <= S_READ_A;
                    end
                end

                S_DONE: begin
                    done <= 1'b1;
                end

            endcase
        end
    end

endmodule

leNET_RTL_v1_seq/tb/tb_avgpool.v
// ============================================================
// tb_avgpool.v — Testbench for Average Pooling (Pool1)
// ============================================================
// Feeds the verified Conv1 output into avgpool, then compares
// all 1176 outputs (6×14×14) against pool1_expected.hex.
// ============================================================

`timescale 1ns / 1ps

module tb_avgpool;

    // ────────────────────────────────────────
    // Clock and reset
    // ────────────────────────────────────────
    reg clk;
    reg rst;
    reg start;

    initial clk = 0;
    always #5 clk = ~clk;  // 100 MHz

    // ────────────────────────────────────────
    // Input memory (Conv1 output, loaded from hex)
    // ────────────────────────────────────────
    localparam IN_SIZE = 4704;  // 6 * 28 * 28
    reg signed [15:0] in_mem [0:IN_SIZE-1];

    initial begin
        $readmemh("conv1_expected.hex", in_mem);
    end

    // DUT reads from in_mem via address port
    wire [12:0] in_addr;
    wire [15:0] in_data = in_mem[in_addr];

    // ────────────────────────────────────────
    // DUT signals
    // ────────────────────────────────────────
    wire        done;
    reg  [12:0] out_addr;
    wire [15:0] out_data;

    // ────────────────────────────────────────
    // Instantiate DUT (Pool1 config)
    // ────────────────────────────────────────
    avgpool #(
        .IN_H  (28),
        .IN_W  (28),
        .N_CH  (6)
    ) dut (
        .clk      (clk),
        .rst      (rst),
        .start    (start),
        .done     (done),
        .in_addr  (in_addr),
        .in_data  (in_data),
        .out_addr (out_addr),
        .out_data (out_data)
    );

    // ────────────────────────────────────────
    // Golden expected output
    // ────────────────────────────────────────
    localparam OUT_SIZE = 1176;  // 6 * 14 * 14

    reg signed [15:0] expected [0:OUT_SIZE-1];

    initial begin
        $readmemh("pool1_expected.hex", expected);
    end

    // ────────────────────────────────────────
    // VCD dump
    // ────────────────────────────────────────
    initial begin
        $dumpfile("avgpool.vcd");
        $dumpvars(0, tb_avgpool);
    end

    // ────────────────────────────────────────
    // Timeout
    // ────────────────────────────────────────
    initial begin
        #500_000;
        $display("ERROR: Simulation timed out.");
        $finish;
    end

    // ────────────────────────────────────────
    // Main test sequence
    // ────────────────────────────────────────
    integer i;
    integer mismatches;

    initial begin
        rst      = 1;
        start    = 0;
        out_addr = 0;
        #100;
        rst = 0;
        #20;

        $display("--------------------------------------------");
        $display(" AvgPool (28x28x6 -> 14x14x6) — Starting...");
        $display("--------------------------------------------");
        start = 1;
        #10;
        start = 0;

        @(posedge done);
        $display(" Done at time %0t ns", $time);
        #20;

        $display("--------------------------------------------");
        $display(" Verifying %0d outputs...", OUT_SIZE);
        $display("--------------------------------------------");

        mismatches = 0;

        for (i = 0; i < OUT_SIZE; i = i + 1) begin
            out_addr = i;
            #10;

            if (out_data !== expected[i]) begin
                mismatches = mismatches + 1;
                if (mismatches <= 20) begin
                    $display(" MISMATCH addr=%0d: RTL=0x%04h (%0d)  Expected=0x%04h (%0d)",
                             i,
                             out_data, $signed(out_data),
                             expected[i], $signed(expected[i]));
                end
            end
        end

        $display("--------------------------------------------");
        if (mismatches == 0)
            $display(" PASS: %0d/%0d outputs match golden model", OUT_SIZE, OUT_SIZE);
        else begin
            $display(" FAIL: %0d mismatches out of %0d", mismatches, OUT_SIZE);
            if (mismatches > 20)
                $display("       (only first 20 shown)");
        end
        $display("--------------------------------------------");

        #100;
        $finish;
    end

endmodule

leNET_RTL_v1_seq/build/avgpool.vcd
$date
	Sat Aug 29 13:59:20 2026
$end
$version
	ModelSim Version 2020.1
$end
$timescale
	1ps
$end

$scope module tb_avgpool $end
$var parameter 32 ! IN_SIZE $end
$var parameter 32 " OUT_SIZE $end
$var reg 1 # clk $end
$var reg 1 $ rst $end
$var reg 1 % start $end
$var wire 1 & in_addr [12] $end
$var wire 1 ' in_addr [11] $end
$var wire 1 ( in_addr [10] $end
$var wire 1 ) in_addr [9] $end
$var wire 1 * in_addr [8] $end
$var wire 1 + in_addr [7] $end
$var wire 1 , in_addr [6] $end
$var wire 1 - in_addr [5] $end
$var wire 1 . in_addr [4] $end
$var wire 1 / in_addr [3] $end
$var wire 1 0 in_addr [2] $end
$var wire 1 1 in_addr [1] $end
$var wire 1 2 in_addr [0] $end
$var wire 1 3 in_data [15] $end
$var wire 1 4 in_data [14] $end
$var wire 1 5 in_data [13] $end
$var wire 1 6 in_data [12] $end
$var wire 1 7 in_data [11] $end
$var wire 1 8 in_data [10] $end
$var wire 1 9 in_data [9] $end
$var wire 1 : in_data [8] $end
$var wire 1 ; in_data [7] $end
$var wire 1 < in_data [6] $end
$var wire 1 = in_data [5] $end
$var wire 1 > in_data [4] $end
$var wire 1 ? in_data [3] $end
$var wire 1 @ in_data [2] $end
$var wire 1 A in_data [1] $end
$var wire 1 B in_data [0] $end
$var wire 1 C done $end
$var reg 13 D out_addr [12:0] $end
$var wire 1 E out_data [15] $end
$var wire 1 F out_data [14] $end
$var wire 1 G out_data [13] $end
$var wire 1 H out_data [12] $end
$var wire 1 I out_data [11] $end
$var wire 1 J out_data [10] $end
$var wire 1 K out_data [9] $end
$var wire 1 L out_data [8] $end
$var wire 1 M out_data [7] $end
$var wire 1 N out_data [6] $end
$var wire 1 O out_data [5] $end
$var wire 1 P out_data [4] $end
$var wire 1 Q out_data [3] $end
$var wire 1 R out_data [2] $end
$var wire 1 S out_data [1] $end
$var wire 1 T out_data [0] $end
$var integer 32 U i $end
$var integer 32 V mismatches $end

$scope module dut $end
$var parameter 32 W IN_H $end
$var parameter 32 X IN_W $end
$var parameter 32 Y N_CH $end
$var parameter 32 Z OUT_H $end
$var parameter 32 [ OUT_W $end
$var parameter 32 \ OUT_SIZE $end
$var parameter 3 ] S_IDLE $end
$var parameter 3 ^ S_READ_A $end
$var parameter 3 _ S_READ_B $end
$var parameter 3 ` S_READ_C $end
$var parameter 3 a S_READ_D $end
$var parameter 3 b S_WRITE $end
$var parameter 3 c S_DONE $end
$var wire 1 d clk $end
$var wire 1 e rst $end
$var wire 1 f start $end
$var reg 1 g done $end
$var wire 1 & in_addr [12] $end
$var wire 1 ' in_addr [11] $end
$var wire 1 ( in_addr [10] $end
$var wire 1 ) in_addr [9] $end
$var wire 1 * in_addr [8] $end
$var wire 1 + in_addr [7] $end
$var wire 1 , in_addr [6] $end
$var wire 1 - in_addr [5] $end
$var wire 1 . in_addr [4] $end
$var wire 1 / in_addr [3] $end
$var wire 1 0 in_addr [2] $end
$var wire 1 1 in_addr [1] $end
$var wire 1 2 in_addr [0] $end
$var wire 1 3 in_data [15] $end
$var wire 1 4 in_data [14] $end
$var wire 1 5 in_data [13] $end
$var wire 1 6 in_data [12] $end
$var wire 1 7 in_data [11] $end
$var wire 1 8 in_data [10] $end
$var wire 1 9 in_data [9] $end
$var wire 1 : in_data [8] $end
$var wire 1 ; in_data [7] $end
$var wire 1 < in_data [6] $end
$var wire 1 = in_data [5] $end
$var wire 1 > in_data [4] $end
$var wire 1 ? in_data [3] $end
$var wire 1 @ in_data [2] $end
$var wire 1 A in_data [1] $end
$var wire 1 B in_data [0] $end
$var wire 1 h out_addr [12] $end
$var wire 1 i out_addr [11] $end
$var wire 1 j out_addr [10] $end
$var wire 1 k out_addr [9] $end
$var wire 1 l out_addr [8] $end
$var wire 1 m out_addr [7] $end
$var wire 1 n out_addr [6] $end
$var wire 1 o out_addr [5] $end
$var wire 1 p out_addr [4] $end
$var wire 1 q out_addr [3] $end
$var wire 1 r out_addr [2] $end
$var wire 1 s out_addr [1] $end
$var wire 1 t out_addr [0] $end
$var wire 1 E out_data [15] $end
$var wire 1 F out_data [14] $end
$var wire 1 G out_data [13] $end
$var wire 1 H out_data [12] $end
$var wire 1 I out_data [11] $end
$var wire 1 J out_data [10] $end
$var wire 1 K out_data [9] $end
$var wire 1 L out_data [8] $end
$var wire 1 M out_data [7] $end
$var wire 1 N out_data [6] $end
$var wire 1 O out_data [5] $end
$var wire 1 P out_data [4] $end
$var wire 1 Q out_data [3] $end
$var wire 1 R out_data [2] $end
$var wire 1 S out_data [1] $end
$var wire 1 T out_data [0] $end
$var reg 3 u state [2:0] $end
$var reg 5 v ch [4:0] $end
$var reg 5 w row [4:0] $end
$var reg 5 x col [4:0] $end
$var reg 18 y acc [17:0] $end
$var reg 13 z rd_addr [12:0] $end
$var wire 1 { base_r [4] $end
$var wire 1 | base_r [3] $end
$var wire 1 } base_r [2] $end
$var wire 1 ~ base_r [1] $end
$var wire 1 !! base_r [0] $end
$var wire 1 "! base_c [4] $end
$var wire 1 #! base_c [3] $end
$var wire 1 $! base_c [2] $end
$var wire 1 %! base_c [1] $end
$var wire 1 &! base_c [0] $end
$var wire 1 '! wr_addr [12] $end
$var wire 1 (! wr_addr [11] $end
$var wire 1 )! wr_addr [10] $end
$var wire 1 *! wr_addr [9] $end
$var wire 1 +! wr_addr [8] $end
$var wire 1 ,! wr_addr [7] $end
$var wire 1 -! wr_addr [6] $end
$var wire 1 .! wr_addr [5] $end
$var wire 1 /! wr_addr [4] $end
$var wire 1 0! wr_addr [3] $end
$var wire 1 1! wr_addr [2] $end
$var wire 1 2! wr_addr [1] $end
$var wire 1 3! wr_addr [0] $end
$var wire 1 4! avg_result [15] $end
$var wire 1 5! avg_result [14] $end
$var wire 1 6! avg_result [13] $end
$var wire 1 7! avg_result [12] $end
$var wire 1 8! avg_result [11] $end
$var wire 1 9! avg_result [10] $end
$var wire 1 :! avg_result [9] $end
$var wire 1 ;! avg_result [8] $end
$var wire 1 <! avg_result [7] $end
$var wire 1 =! avg_result [6] $end
$var wire 1 >! avg_result [5] $end
$var wire 1 ?! avg_result [4] $end
$var wire 1 @! avg_result [3] $end
$var wire 1 A! avg_result [2] $end
$var wire 1 B! avg_result [1] $end
$var wire 1 C! avg_result [0] $end
$upscope $end
$upscope $end
$enddefinitions $end
#0
$dumpvars
0#
1$
0%
b0 D
xg
bx u
bx v
bx w
bx x
bx y
bx z
b1001001100000 !
b10010011000 "
b11100 W
b11100 X
b110 Y
b1110 Z
b1110 [
b10010011000 \
b0 ]
b1 ^
b10 _
b11 `
b100 a
b101 b
b110 c
bx U
bx V
x2
x1
x0
x/
x.
x-
x,
x+
x*
x)
x(
x'
x&
xB
xA
x@
x?
x>
x=
x<
x;
x:
x9
x8
x7
x6
x5
x4
x3
xC
xT
xS
xR
xQ
xP
xO
xN
xM
xL
xK
xJ
xI
xH
xG
xF
xE
x!!
x~
x}
x|
x{
x&!
x%!
x$!
x#!
x"!
x3!
x2!
x1!
x0!
x/!
x.!
x-!
x,!
x+!
x*!
x)!
x(!
x'!
xC!
xB!
xA!
x@!
x?!
x>!
x=!
x<!
x;!
x:!
x9!
x8!
x7!
x6!
x5!
x4!
0t
0s
0r
0q
0p
0o
0n
0m
0l
0k
0j
0i
0h
0f
1e
0d
$end
#5000
1#
1d
b0 u
0g
b0 v
b0 w
b0 x
b0 y
b0 z
02
01
00
0/
0.
0-
0,
0+
0*
0)
0(
0'
0&
0C!
0B!
0A!
0@!
0?!
0>!
0=!
0<!
0;!
0:!
09!
08!
07!
06!
05!
04!
0&!
0%!
0$!
0#!
0"!
0!!
0~
0}
0|
0{
03!
02!
01!
00!
0/!
0.!
0-!
0,!
0+!
0*!
0)!
0(!
0'!
0B
0A
0@
0?
0>
0=
0<
0;
0:
09
08
07
06
05
04
03
0C
#10000
0#
0d
#15000
1#
1d
#20000
0#
0d
#25000
1#
1d
#30000
0#
0d
#35000
1#
1d
#40000
0#
0d
#45000
1#
1d
#50000
0#
0d
#55000
1#
1d
#60000
0#
0d
#65000
1#
1d
#70000
0#
0d
#75000
1#
1d
#80000
0#
0d
#85000
1#
1d
#90000
0#
0d
#95000
1#
1d
#100000
0$
0#
0e
0d
#105000
1#
1d
#110000
0#
0d
#115000
1#
1d
#120000
1%
0#
1f
0d
#125000
1#
1d
b1 u
#130000
0%
0#
0f
0d
#135000
1#
1d
b10 u
#140000
0#
0d
#145000
1#
1d
b1 z
b11 u
12
#150000
0#
0d
#155000
1#
1d
b11100 z
b100 u
02
10
1/
1.
#160000
0#
0d
#165000
1#
1d
b11101 z
b101 u
12
#170000
0#
0d
#175000
1#
1d
b1 x
b1 u
1%!
13!
0T
0S
0R
0Q
0P
0O
0N
0M
0L
0K
0J
0I
0H
0G
0F
0E
#180000
0#
0d
#185000
1#
1d
b10 z
b10 u
02
11
00
0/
0.
#190000
0#
0d
#195000
1#
1d
b11 z
b11 u
12
#200000
0#
0d
#205000
1#
1d
b11110 z
b100 u
02
10
1/
1.
#210000
0#
0d
#215000
1#
1d
b11111 z
b101 u
12
#220000
0#
0d
#225000
1#
1d
b10 x
b1 u
0%!
1$!
03!
12!
#230000
0#
0d
#235000
1#
1d
b100 z
b10 u
02
01
0/
0.
#240000
0#
0d
#245000
1#
1d
b101 z
b11 u
12
#250000
0#
0d
#255000
1#
1d
b100000 z
b100 u
02
00
1-
#260000
0#
0d
#265000
1#
1d
b100001 z
b101 u
12
#270000
0#
0d
#275000
1#
1d
b11 x
b1 u
1%!
13!
#280000
0#
0d
#285000
1#
1d
b110 z
b10 u
02
11
10
0-
#290000
0#
0d
#295000
1#
1d
b111 z
b11 u
12
#300000
0#
0d
#305000
1#
1d
b100010 z
b100 u
02
00
1-
#310000
0#
0d
#315000
1#
1d
b100011 z
b101 u
12
#320000
0#
0d
#325000
1#
1d
b100 x
b1 u
0%!
0$!
1#!
03!
02!
11!
#330000
0#
0d
#335000
1#
1d
b1000 z
b10 u
02
01
1/
0-
#340000
0#
0d
#345000
1#
1d
b1001 z
b11 u
12
#350000
0#
0d
#355000
1#
1d
b100100 z
b100 u
02
10
0/
1-
#360000
0#
0d
#365000
1#
1d
b100101 z
b101 u
12
#370000
0#
0d
#375000
1#
1d
b101 x
b1 u
1%!
13!
#380000
0#
0d
#385000
1#
1d
b1010 z
b10 u
02
11
00
1/
0-
#390000
0#
0d
#395000
1#
1d
b1011 z
b11 u
12
#400000
0#
0d
#405000
1#
1d
b100110 z
b100 u
02
10
0/
1-
#410000
0#
0d
#415000
1#
1d
b100111 z
b101 u
12
#420000
0#
0d
#425000
1#
1d
b110 x
b1 u
0%!
1$!
03!
12!
#430000
0#
0d
#435000
1#
1d
b1100 z
b10 u
02
01
1/
0-
#440000
0#
0d
#445000
1#
1d
b1101 z
b11 u
12
#450000
0#
0d
#455000
1#
1d
b101000 z
b100 u
02
00
1-
#460000
0#
0d
#465000
1#
1d
b101001 z
b101 u
12
#470000
0#
0d
#475000
1#
1d
b111 x
b1 u
1%!
13!
#480000
0#
0d
#485000
1#
1d
b1110 z
b10 u
02
11
10
0-
#490000
0#
0d
#495000
1#
1d
b1111 z
b11 u
12
#500000
0#
0d
#505000
1#
1d
b101010 z
b100 u
02
00
1-
#510000
0#
0d
#515000
1#
1d
b101011 z
b101 u
12
#520000
0#
0d
#525000
1#
1d
b1000 x
b1 u
0%!
0$!
0#!
1"!
03!
02!
01!
10!
#530000
0#
0d
#535000
1#
1d
b10000 z
b10 u
02
01
0/
1.
0-
#540000
0#
0d
#545000
1#
1d
b10001 z
b11 u
12
#550000
0#
0d
#555000
1#
1d
b101100 z
b100 u
02
10
1/
0.
1-
#560000
0#
0d
#565000
1#
1d
b101101 z
b101 u
12
#570000
0#
0d
#575000
1#
1d
b1001 x
b1 u
1%!
13!
#580000
0#
0d
#585000
1#
1d
b10010 z
b10 u
02
11
00
0/
1.
0-
#590000
0#
0d
#595000
1#
1d
b10011 z
b11 u
12
#600000
0#
0d
#605000
1#
1d
b101110 z
b100 u
02
10
1/
0.
1-
#610000
0#
0d
#615000
1#
1d
b101111 z
b101 u
12
#620000
0#
0d
#625000
1#
1d
b1010 x
b1 u
0%!
1$!
03!
12!
#630000
0#
0d
#635000
1#
1d
b10100 z
b10 u
02
01
0/
1.
0-
#640000
0#
0d
#645000
1#
1d
b10101 z
b11 u
12
#650000
0#
0d
#655000
1#
1d
b110000 z
b100 u
02
00
1-
#660000
0#
0d
#665000
1#
1d
b110001 z
b101 u
12
#670000
0#
0d
#675000
1#
1d
b1011 x
b1 u
1%!
13!
#680000
0#
0d
#685000
1#
1d
b10110 z
b10 u
02
11
10
0-
#690000
0#
0d
#695000
1#
1d
b10111 z
b11 u
12
#700000
0#
0d
#705000
1#
1d
b110010 z
b100 u
02
00
1-
#710000
0#
0d
#715000
1#
1d
b110011 z
b101 u
12
#720000
0#
0d
#725000
1#
1d
b1100 x
b1 u
0%!
0$!
1#!
03!
02!
11!
#730000
0#
0d
#735000
1#
1d
b11000 z
b10 u
02
01
1/
0-
#740000
0#
0d
#745000
1#
1d
b11001 z
b11 u
12
#750000
0#
0d
#755000
1#
1d
b110100 z
b100 u
02
10
0/
1-
#760000
0#
0d
#765000
1#
1d
b110101 z
b101 u
12
#770000
0#
0d
#775000
1#
1d
b1101 x
b1 u
1%!
13!
#780000
0#
0d
#785000
1#
1d
b11010 z
b10 u
02
11
00
1/
0-
#790000
0#
0d
#795000
1#
1d
b11011 z
b11 u
12
#800000
0#
0d
#805000
1#
1d
b110110 z
b100 u
02
10
0/
1-
#810000
0#
0d
#815000
1#
1d
b110111 z
b101 u
12
#820000
0#
0d
#825000
1#
1d
b0 x
b1 w
b1 u
1~
0%!
0#!
0"!
03!
12!
#830000
0#
0d
#835000
1#
1d
b111000 z
b10 u
02
01
00
1/
#840000
0#
0d
#845000
1#
1d
b111001 z
b11 u
12
#850000
0#
0d
#855000
1#
1d
b1010100 z
b100 u
02
10
0/
0-
1,
#860000
0#
0d
#865000
1#
1d
b1010101 z
b101 u
12
#870000
0#
0d
#875000
1#
1d
b1 x
b1 u
1%!
13!
#880000
0#
0d
#885000
1#
1d
b111010 z
b10 u
02
11
00
1/
1-
0,
#890000
0#
0d
#895000
1#
1d
b111011 z
b11 u
12
#900000
0#
0d
#905000
1#
1d
b1010110 z
b100 u
02
10
0/
0-
1,
#910000
0#
0d
#915000
1#
1d
b1010111 z
b101 u
12
#920000
0#
0d
#925000
1#
1d
b10 x
b1 u
0%!
1$!
03!
02!
01!
00!
1/!
#930000
0#
0d
#935000
1#
1d
b111100 z
b10 u
02
01
1/
1-
0,
#940000
0#
0d
#945000
1#
1d
b111101 z
b11 u
12
#950000
0#
0d
#955000
1#
1d
b1011000 z
b100 u
02
00
0-
1,
#960000
0#
0d
#965000
1#
1d
b1011001 z
b101 u
12
#970000
0#
0d
#975000
1#
1d
b11 x
b1 u
1%!
13!
#980000
0#
0d
#985000
1#
1d
b111110 z
b10 u
02
11
10
1-
0,
#990000
0#
0d
#995000
1#
1d
b111111 z
b11 u
12
#1000000
0#
0d
#1005000
1#
1d
b1011010 z
b100 u
02
00
0-
1,
#1010000
0#
0d
#1015000
1#
1d
b1011011 z
b101 u
12
#1020000
0#
0d
#1025000
1#
1d
b100 x
b1 u
0%!
0$!
1#!
03!
12!
#1030000
0#
0d
#1035000
1#
1d
b1000000 z
b10 u
02
01
0/
0.
#1040000
0#
0d
#1045000
1#
1d
b1000001 z
b11 u
12
#1050000
0#
0d
#1055000
1#
1d
b1011100 z
b100 u
02
10
1/
1.
#1060000
0#
0d
#1065000
1#
1d
b1011101 z
b101 u
12
#1070000
0#
0d
#1075000
1#
1d
b101 x
b1 u
1%!
13!
#1080000
0#
0d
#1085000
1#
1d
b1000010 z
b10 u
02
11
00
0/
0.
#1090000
0#
0d
#1095000
1#
1d
b1000011 z
b11 u
12
#1100000
0#
0d
#1105000
1#
1d
b1011110 z
b100 u
02
10
1/
1.
#1110000
0#
0d
#1115000
1#
1d
b1011111 z
b101 u
12
#1120000
0#
0d
#1125000
1#
1d
b110 x
b1 u
0%!
1$!
03!
02!
11!
#1130000
0#
0d
#1135000
1#
1d
b1000100 z
b10 u
02
01
0/
0.
#1140000
0#
0d
#1145000
1#
1d
b1000101 z
b11 u
12
#1150000
0#
0d
#1155000
1#
1d
b1100000 z
b100 u
02
00
1-
#1160000
0#
0d
#1165000
1#
1d
b1100001 z
b101 u
12
#1170000
0#
0d
#1175000
1#
1d
b111 x
b1 u
1%!
13!
#1180000
0#
0d
#1185000
1#
1d
b1000110 z
b10 u
02
11
10
0-
#1190000
0#
0d
#1195000
1#
1d
b1000111 z
b11 u
12
#1200000
0#
0d
#1205000
1#
1d
b1100010 z
b100 u
02
00
1-
#1210000
0#
0d
#1215000
1#
1d
b1100011 z
b101 u
12
#1220000
0#
0d
#1225000
1#
1d
b1000 x
b1 u
0%!
0$!
0#!
1"!
03!
12!
#1230000
0#
0d
#1235000
1#
1d
b1001000 z
b10 u
02
01
1/
0-
#1240000
0#
0d
#1245000
1#
1d
b1001001 z
b11 u
12
#1250000
0#
0d
#1255000
1#
1d
b1100100 z
b100 u
02
10
0/
1-
#1260000
0#
0d
#1265000
1#
1d
b1100101 z
b101 u
12
#1270000
0#
0d
#1275000
1#
1d
b1001 x
b1 u
1%!
13!
#1280000
0#
0d
#1285000
1#
1d
b1001010 z
b10 u
02
11
00
1/
0-
#1290000
0#
0d
#1295000
1#
1d
b1001011 z
b11 u
12
#1300000
0#
0d
#1305000
1#
1d
b1100110 z
b100 u
02
10
0/
1-
#1310000
0#
0d
#1315000
1#
1d
b1100111 z
b101 u
12
#1320000
0#
0d
#1325000
1#
1d
b1010 x
b1 u
0%!
1$!
03!
02!
01!
10!
#1330000
0#
0d
#1335000
1#
1d
b1001100 z
b10 u
02
01
1/
0-
#1340000
0#
0d
#1345000
1#
1d
b1001101 z
b11 u
12
#1350000
0#
0d
#1355000
1#
1d
b1101000 z
b100 u
02
00
1-
#1360000
0#
0d
#1365000
1#
1d
b1101001 z
b101 u
12
#1370000
0#
0d
#1375000
1#
1d
b1011 x
b1 u
1%!
13!
#1380000
0#
0d
#1385000
1#
1d
b1001110 z
b10 u
02
11
10
0-
#1390000
0#
0d
#1395000
1#
1d
b1001111 z
b11 u
12
#1400000
0#
0d
#1405000
1#
1d
b1101010 z
b100 u
02
00
1-
#1410000
0#
0d
#1415000
1#
1d
b1101011 z
b101 u
12
#1420000
0#
0d
#1425000
1#
1d
b1100 x
b1 u
0%!
0$!
1#!
03!
12!
#1430000
0#
0d
#1435000
1#
1d
b1010000 z
b10 u
02
01
0/
1.
0-
#1440000
0#
0d
#1445000
1#
1d
b1010001 z
b11 u
12
#1450000
0#
0d
#1455000
1#
1d
b1101100 z
b100 u
02
10
1/
0.
1-
#1460000
0#
0d
#1465000
1#
1d
b1101101 z
b101 u
12
#1470000
0#
0d
#1475000
1#
1d
b1101 x
b1 u
1%!
13!
#1480000
0#
0d
#1485000
1#
1d
b1010010 z
b10 u
02
11
00
0/
1.
0-
#1490000
0#
0d
#1495000
1#
1d
b1010011 z
b11 u
12
#1500000
0#
0d
#1505000
1#
1d
b1101110 z
b100 u
02
10
1/
0.
1-
#1510000
0#
0d
#1515000
1#
1d
b1101111 z
b101 u
12
#1520000
0#
0d
#1525000
1#
1d
b0 x
b10 w
b1 u
0~
1}
0%!
0#!
0"!
03!
02!
11!
#1530000
0#
0d
#1535000
1#
1d
b1110000 z
b10 u
02
01
00
0/
1.
#1540000
0#
0d
#1545000
1#
1d
b1110001 z
b11 u
12
#1550000
0#
0d
#1555000
1#
1d
b10001100 z
b100 u
02
10
1/
0.
0-
0,
1+
#1560000
0#
0d
#1565000
1#
1d
b10001101 z
b101 u
12
#1570000
0#
0d
#1575000
1#
1d
b1 x
b1 u
1%!
13!
#1580000
0#
0d
#1585000
1#
1d
b1110010 z
b10 u
02
11
00
0/
1.
1-
1,
0+
#1590000
0#
0d
#1595000
1#
1d
b1110011 z
b11 u
12
#1600000
0#
0d
#1605000
1#
1d
b10001110 z
b100 u
02
10
1/
0.
0-
0,
1+
#1610000
0#
0d
#1615000
1#
1d
b10001111 z
b101 u
12
#1620000
0#
0d
#1625000
1#
1d
b10 x
b1 u
0%!
1$!
03!
12!
#1630000
0#
0d
#1635000
1#
1d
b1110100 z
b10 u
02
01
0/
1.
1-
1,
0+
#1640000
0#
0d
#1645000
1#
1d
b1110101 z
b11 u
12
#1650000
0#
0d
#1655000
1#
1d
b10010000 z
b100 u
02
00
0-
0,
1+
#1660000
0#
0d
#1665000
1#
1d
b10010001 z
b101 u
12
1B
1?
1=
#1670000
0#
0d
#1675000
1#
1d
b101001 y
b11 x
b0 y
b1 u
1%!
13!
#1680000
0#
0d
#1685000
1#
1d
b1110110 z
b10 u
02
11
10
1-
1,
0+
0B
0?
0=
#1690000
0#
0d
#1695000
1#
1d
b1110111 z
b11 u
12
#1700000
0#
0d
#1705000
1#
1d
b10010010 z
b100 u
02
00
0-
0,
1+
1A
1>
#1710000
0#
0d
#1715000
1#
1d
b10010 y
b10010011 z
b101 u
12
1C!
1A!
0A
0>
#1720000
0#
0d
#1725000
1#
1d
b100 x
b0 y
b1 u
0C!
0A!
0%!
0$!
1#!
03!
02!
01!
00!
0/!
1.!
#1730000
0#
0d
#1735000
1#
1d
b1111000 z
b10 u
02
01
1/
1-
1,
0+
#1740000
0#
0d
#1745000
1#
1d
b1111001 z
b11 u
12
#1750000
0#
0d
